pclines/__init__.py
pclines/accumulator.py
pclines/rasterizer.py
pclines/utils.py
pclines-1.0.2.dist-info/LICENSE
pclines-1.0.2.dist-info/METADATA
pclines-1.0.2.dist-info/WHEEL
pclines-1.0.2.dist-info/top_level.txt
pclines-1.0.2.dist-info/RECORD
