Metadata-Version: 2.1
Name: pclines
Version: 1.0.2
Summary: PCLines transform for python
Home-page: https://github.com/RomanJuranek/pclines-python
Author: Roman Juranek
Author-email: ijuranek@fit.vutbr.cz
License: BSD3
Project-URL: Bug reports, https://github.com/RomanJuranek/pclines-python/issues
Keywords: pclines,hough transform,line detection
Platform: UNKNOWN
Requires-Python: >=3.6
Requires-Dist: numpy
Requires-Dist: numba
Requires-Dist: scikit-image
